{
  "lessons": {
    "26715": {
      "actual": {
        "lesson_id": 26715,
        "datetime_from": "2023-11-02 07:40:00",
        "datetime_to": "2023-11-02 08:25:00",
        "name": "ARO - SEPT",
        "lessonjoin_id": null,
        "courses": {
          "14512": {
            "course_id": "14512",
            "course_code": "ARO - SEPT",
            "course_type_id": "2"
          }
        },
        "teachers": {
          "2923": {
            "person_id": "2923",
            "person_abbr": "Evan"
          }
        },
        "students": {
          "122266": {
            "subject_id": "122266",
            "subject_name": "Žáci SEPT"
          }
        },
        "rooms": {
          "47": {
            "room_id": "47",
            "room_name": "B1"
          }
        }
      },
      "scheduled": {
        "lesson_id": 26715,
        "datetime_from": "2023-11-02 07:40:00",
        "datetime_to": "2023-11-02 08:25:00",
        "name": "ARO - SEPT",
        "lessonjoin_id": null,
        "courses": {
          "14512": {
            "course_id": "14512",
            "course_code": "ARO - SEPT",
            "course_type_id": "2"
          }
        },
        "teachers": {
          "2923": {
            "person_id": "2923",
            "person_abbr": "Evan"
          }
        },
        "students": {
          "122266": {
            "subject_id": "122266",
            "subject_name": "Žáci SEPT"
          }
        },
        "rooms": {
          "47": {
            "room_id": "47",
            "room_name": "B1"
          }
        }
      }
    },
    "67714": {
      "actual": {
        "lesson_id": 67714,
        "datetime_from": "2023-11-02 08:30:00",
        "datetime_to": "2023-11-02 09:15:00",
        "name": "ANJx - SEPT",
        "lessonjoin_id": null,
        "courses": {
          "14786": {
            "course_id": "14786",
            "course_code": "ANJx - SEPT",
            "course_type_id": "2"
          }
        },
        "teachers": {
          "2923": {
            "person_id": "2923",
            "person_abbr": "Evan"
          }
        },
        "students": {
          "126379": {
            "subject_id": "126379",
            "subject_name": "Žáci SEPT - ANJx"
          }
        },
        "rooms": {
          "47": {
            "room_id": "47",
            "room_name": "B1"
          }
        }
      },
      "scheduled": {
        "lesson_id": 67714,
        "datetime_from": "2023-11-02 08:30:00",
        "datetime_to": "2023-11-02 09:15:00",
        "name": "ANJx - SEPT",
        "lessonjoin_id": null,
        "courses": {
          "14786": {
            "course_id": "14786",
            "course_code": "ANJx - SEPT",
            "course_type_id": "2"
          }
        },
        "teachers": {
          "2923": {
            "person_id": "2923",
            "person_abbr": "Evan"
          }
        },
        "students": {
          "126379": {
            "subject_id": "126379",
            "subject_name": "Žáci SEPT - ANJx"
          }
        },
        "rooms": {
          "47": {
            "room_id": "47",
            "room_name": "B1"
          }
        }
      }
    },
    "10977": {
      "actual": {
        "lesson_id": 10977,
        "datetime_from": null,
        "datetime_to": null,
        "name": "BUSh - IB.1, IB1",
        "lessonjoin_id": null,
        "courses": {
          "15125": {
            "course_id": "15125",
            "course_code": "BUSh - IB.1, IB1",
            "course_type_id": "2"
          }
        },
        "students": {
          "130815": {
            "subject_id": "130815",
            "subject_name": "Žáci IB.1 - BUSh"
          },
          "130819": {
            "subject_id": "130819",
            "subject_name": "Žáci IB1 - BUSh"
          }
        },
        "rooms": {
          "47": {
            "room_id": "47",
            "room_name": "B1"
          }
        }
      },
      "scheduled": {
        "lesson_id": 10977,
        "datetime_from": "2023-11-02 09:25:00",
        "datetime_to": "2023-11-02 10:10:00",
        "name": "BUSh - IB.1, IB1",
        "lessonjoin_id": null,
        "courses": {
          "15125": {
            "course_id": "15125",
            "course_code": "BUSh - IB.1, IB1",
            "course_type_id": "2"
          }
        },
        "teachers": {
          "6901": {
            "person_id": "6901",
            "person_abbr": "Lib"
          }
        },
        "students": {
          "130815": {
            "subject_id": "130815",
            "subject_name": "Žáci IB.1 - BUSh"
          },
          "130819": {
            "subject_id": "130819",
            "subject_name": "Žáci IB1 - BUSh"
          }
        },
        "rooms": {
          "47": {
            "room_id": "47",
            "room_name": "B1"
          }
        }
      }
    },
    "11020": {
      "actual": {
        "lesson_id": 11020,
        "datetime_from": null,
        "datetime_to": null,
        "name": "BUSh - IB.1, IB1",
        "lessonjoin_id": null,
        "courses": {
          "15125": {
            "course_id": "15125",
            "course_code": "BUSh - IB.1, IB1",
            "course_type_id": "2"
          }
        },
        "students": {
          "130815": {
            "subject_id": "130815",
            "subject_name": "Žáci IB.1 - BUSh"
          },
          "130819": {
            "subject_id": "130819",
            "subject_name": "Žáci IB1 - BUSh"
          }
        },
        "rooms": {
          "47": {
            "room_id": "47",
            "room_name": "B1"
          }
        }
      },
      "scheduled": {
        "lesson_id": 11020,
        "datetime_from": "2023-11-02 10:20:00",
        "datetime_to": "2023-11-02 11:05:00",
        "name": "BUSh - IB.1, IB1",
        "lessonjoin_id": null,
        "courses": {
          "15125": {
            "course_id": "15125",
            "course_code": "BUSh - IB.1, IB1",
            "course_type_id": "2"
          }
        },
        "teachers": {
          "6901": {
            "person_id": "6901",
            "person_abbr": "Lib"
          }
        },
        "students": {
          "130815": {
            "subject_id": "130815",
            "subject_name": "Žáci IB.1 - BUSh"
          },
          "130819": {
            "subject_id": "130819",
            "subject_name": "Žáci IB1 - BUSh"
          }
        },
        "rooms": {
          "47": {
            "room_id": "47",
            "room_name": "B1"
          }
        }
      }
    },
    "71756": {
      "actual": {
        "lesson_id": 71756,
        "datetime_from": "2023-11-02 11:20:00",
        "datetime_to": "2023-11-02 12:05:00",
        "name": "CAL 2 - IB.1, IB1",
        "lessonjoin_id": null,
        "courses": {
          "15137": {
            "course_id": "15137",
            "course_code": "CAL 2 - IB.1, IB1",
            "course_type_id": "2"
          }
        },
        "teachers": {
          "2921": {
            "person_id": "2921",
            "person_abbr": "Zgr"
          }
        },
        "students": {
          "125503": {
            "subject_id": "125503",
            "subject_name": "Žáci IB1 - CAL 2"
          },
          "126155": {
            "subject_id": "126155",
            "subject_name": "Žáci IB.1 - CAL 2"
          }
        },
        "rooms": {
          "47": {
            "room_id": "47",
            "room_name": "B1"
          }
        }
      },
      "scheduled": {
        "lesson_id": 71756,
        "datetime_from": "2023-11-02 11:20:00",
        "datetime_to": "2023-11-02 12:05:00",
        "name": "CAL 2 - IB.1, IB1",
        "lessonjoin_id": null,
        "courses": {
          "15137": {
            "course_id": "15137",
            "course_code": "CAL 2 - IB.1, IB1",
            "course_type_id": "2"
          }
        },
        "teachers": {
          "2921": {
            "person_id": "2921",
            "person_abbr": "Zgr"
          }
        },
        "students": {
          "125503": {
            "subject_id": "125503",
            "subject_name": "Žáci IB1 - CAL 2"
          },
          "126155": {
            "subject_id": "126155",
            "subject_name": "Žáci IB.1 - CAL 2"
          }
        },
        "rooms": {
          "47": {
            "room_id": "47",
            "room_name": "B1"
          }
        }
      }
    },
    "71799": {
      "actual": {
        "lesson_id": 71799,
        "datetime_from": "2023-11-02 12:15:00",
        "datetime_to": "2023-11-02 13:00:00",
        "name": "CAL 1 - IB.1, IB1",
        "lessonjoin_id": null,
        "courses": {
          "15136": {
            "course_id": "15136",
            "course_code": "CAL 1 - IB.1, IB1",
            "course_type_id": "2"
          }
        },
        "teachers": {
          "2921": {
            "person_id": "2921",
            "person_abbr": "Zgr"
          }
        },
        "students": {
          "125491": {
            "subject_id": "125491",
            "subject_name": "Žáci IB1 - CAL 1"
          },
          "129979": {
            "subject_id": "129979",
            "subject_name": "Žáci IB.1 - CAL 1"
          }
        },
        "rooms": {
          "47": {
            "room_id": "47",
            "room_name": "B1"
          }
        }
      },
      "scheduled": {
        "lesson_id": 71799,
        "datetime_from": "2023-11-02 12:15:00",
        "datetime_to": "2023-11-02 13:00:00",
        "name": "CAL 1 - IB.1, IB1",
        "lessonjoin_id": null,
        "courses": {
          "15136": {
            "course_id": "15136",
            "course_code": "CAL 1 - IB.1, IB1",
            "course_type_id": "2"
          }
        },
        "teachers": {
          "2921": {
            "person_id": "2921",
            "person_abbr": "Zgr"
          }
        },
        "students": {
          "125491": {
            "subject_id": "125491",
            "subject_name": "Žáci IB1 - CAL 1"
          },
          "129979": {
            "subject_id": "129979",
            "subject_name": "Žáci IB.1 - CAL 1"
          }
        },
        "rooms": {
          "47": {
            "room_id": "47",
            "room_name": "B1"
          }
        }
      }
    },
    "9171": {
      "actual": {
        "lesson_id": 9171,
        "datetime_from": "2023-11-02 13:10:00",
        "datetime_to": "2023-11-02 13:55:00",
        "name": "ENG HL 2 - IB.1, IB1",
        "lessonjoin_id": null,
        "courses": {
          "15154": {
            "course_id": "15154",
            "course_code": "ENG HL 2 - IB.1, IB1",
            "course_type_id": "2"
          }
        },
        "teachers": {
          "2846": {
            "person_id": "2846",
            "person_abbr": "Odo"
          }
        },
        "students": {
          "130179": {
            "subject_id": "130179",
            "subject_name": "Žáci IB.1 - ENG HL 2"
          },
          "130183": {
            "subject_id": "130183",
            "subject_name": "Žáci IB1 - ENG HL 2"
          }
        },
        "rooms": {
          "47": {
            "room_id": "47",
            "room_name": "B1"
          }
        }
      },
      "scheduled": {
        "lesson_id": 9171,
        "datetime_from": "2023-11-02 13:10:00",
        "datetime_to": "2023-11-02 13:55:00",
        "name": "ENG HL 2 - IB.1, IB1",
        "lessonjoin_id": null,
        "courses": {
          "15154": {
            "course_id": "15154",
            "course_code": "ENG HL 2 - IB.1, IB1",
            "course_type_id": "2"
          }
        },
        "teachers": {
          "2846": {
            "person_id": "2846",
            "person_abbr": "Odo"
          }
        },
        "students": {
          "130179": {
            "subject_id": "130179",
            "subject_name": "Žáci IB.1 - ENG HL 2"
          },
          "130183": {
            "subject_id": "130183",
            "subject_name": "Žáci IB1 - ENG HL 2"
          }
        },
        "rooms": {
          "47": {
            "room_id": "47",
            "room_name": "B1"
          }
        }
      }
    }
  }
}